LICENSE
MANIFEST.in
Readme.md
setup.cfg
setup.py
pastebinfs/__init__.py
pastebinfs/os.py
pastebinfs/parse_path.py
pastebinfs/sync.py
pastebinfs.egg-info/PKG-INFO
pastebinfs.egg-info/SOURCES.txt
pastebinfs.egg-info/dependency_links.txt
pastebinfs.egg-info/not-zip-safe
pastebinfs.egg-info/requires.txt
pastebinfs.egg-info/top_level.txt
pastebinfs/pastebin/__init__.py
pastebinfs/pastebin/bufferedbyte.py
pastebinfs/pastebin/bufferedtext.py
pastebinfs/pastebin/pastebinapi.py
pastebinfs/pastebin/unbufferedbyte.py
tests/__init__.py
tests/pastebin_api_mock.py
tests/test_auth.py
tests/test_file_modes.py
tests/test_open.py
tests/test_stat.py