Metadata-Version: 2.1
Name: pastebinfs
Version: 0.4
Summary: Using Pastebin pastes as if they were files
Home-page: https://github.com/K0IN/pastebin-as-file
Author: K0IN
Author-email: thisk0in@gmail.com
License: MIT
Keywords: pastebin file file-like
Platform: UNKNOWN
License-File: LICENSE
